gnssvod/__init__.py
gnssvod/analysis/__init__.py
gnssvod/analysis/vod_calc.py
gnssvod/doc/IGS.py
gnssvod/doc/IGSList.txt
gnssvod/doc/__init__.py
gnssvod/download.py
gnssvod/funcs/__init__.py
gnssvod/funcs/checkif.py
gnssvod/funcs/constants.py
gnssvod/funcs/date.py
gnssvod/funcs/filename.py
gnssvod/funcs/interpolation.py
gnssvod/geodesy/__init__.py
gnssvod/geodesy/coordinate.py
gnssvod/geodesy/projection.py
gnssvod/hemistats/__init__.py
gnssvod/hemistats/hemistats.py
gnssvod/io/__init__.py
gnssvod/io/exporters.py
gnssvod/io/io.py
gnssvod/io/manipulate.py
gnssvod/io/preprocess.py
gnssvod/io/readFile.py
gnssvod/plot.py
gnssvod/position/__init__.py
gnssvod/position/atmosphere.py
gnssvod/position/interpolation.py
gnssvod/position/position.py
gnssvod/position/satellite.py
gnssvod-2025.1.2.dist-info/LICENSE
gnssvod-2025.1.2.dist-info/METADATA
gnssvod-2025.1.2.dist-info/WHEEL
gnssvod-2025.1.2.dist-info/RECORD
