Metadata-Version: 2.1
Name: gnssvod
Version: 2025.1.2
Summary: Read GNSS receiver output files and analyse vegetation optical depth (VOD)
License: MIT
Author: Vincent Humphrey
Author-email: vincent.humphrey@meteoswiss.ch
Requires-Python: >=3.9,<4.0
Classifier: License :: OSI Approved :: MIT License
Classifier: Programming Language :: Python :: 3
Classifier: Programming Language :: Python :: 3.9
Classifier: Programming Language :: Python :: 3.10
Classifier: Programming Language :: Python :: 3.11
Classifier: Programming Language :: Python :: 3.12
Classifier: Programming Language :: Python :: 3.13
Requires-Dist: hatanaka (>=2.8.1,<3.0.0)
Requires-Dist: numpy (>=1.25.0,<2.0.0)
Requires-Dist: pyunpack (>=0.3,<0.4)
Requires-Dist: tqdm (>=4.60.0,<5.0.0)
Requires-Dist: xarray[io,parallel] (>=2022.12.0)
